Workbook

Sheet Calculadora
B5: Calculadora de preço de venda
B6: Preencha só as células em vinho claro. O resto calcula sozinho.
B8: 1 · CUSTO DO FORNECEDOR
B9: Preço de custo (fornecedor) | C9: 100 | E9: Valor que o fornecedor cobra por garrafa
B11: 2 · PREMISSAS (mudam pouco, mas dá pra ajustar)
B12: DIFAL | C12: 0.13 | E12: Somado em cima do custo do fornecedor
B13: Markup | C13: 1.6 | E13: Multiplica o custo com DIFAL
B14: Simples Nacional | C14: 0.08 | E14: Sobre o preço de venda
B15: Frete por garrafa | C15: 10 | E15: Valor fixo por garrafa vendida
B17: 3 · CÁLCULO
B18: Custo com DIFAL | C18: =C9*(1+C12) | E18: Custo × (1 + DIFAL)
B19: Preço de venda | C19: =C18*C13 | E19: Custo com DIFAL × markup
B20: (−) Simples Nacional | C20: =-C19*C14 | E20: Preço de venda × Simples
B21: (−) Frete | C21: =-C15 | E21: Fixo por garrafa
B22: (−) Custo com DIFAL | C22: =-C18 | E22: O que pagamos pelo vinho
B24: 4 · O QUE SOBRA PRA NÓS
B25: Lucro por garrafa | C25: =C19+C20+C21+C22 | E25: Venda − Simples − Frete − Custo com DIFAL
B26: Markup final | C26: =IF(C18=0,0,(C19+C20+C21)/C18) | E26: Quanto entra líquido (venda − Simples − frete) ÷ custo com DIFAL
B27: Margem líquida | C27: =IF(C19=0,0,C25/C19) | E27: Lucro ÷ preço de venda
B28: Markup final s/ custo do fornecedor | C28: =IF(C9=0,0,(C19+C20+C21)/C9) | E28: Mesmo cálculo, mas dividindo pelo custo puro (sem DIFAL)
B30: Legenda: células em vinho claro com borda = preencher · demais = fórmula, não editar.
B31: Premissas (DIFAL 13%, markup 1,6, Simples 8%, frete R$ 10) informadas pelo Marcelo em 21/out/2026.

Sheet Lista de vinhos
B4: Precificação em lote
B5: Preencha nome e custo do fornecedor. As premissas vêm da aba Calculadora (DIFAL, markup, Simples e frete) — mudou lá, muda aqui.
B7: Vinho | C7: Custo fornecedor | D7: Custo c/ DIFAL | E7: Preço de venda | F7: Simples | G7: Frete | H7: Lucro / garrafa | I7: Markup final | J7: Margem líquida
B8: Exemplo — Malbec Reserva (apague e use) | C8: 89.9 | D8: =IF($C8="","",C8*(1+Calculadora!$C$12)) | E8: =IF($C8="","",D8*Calculadora!$C$13) | F8: =IF($C8="","",E8*Calculadora!$C$14) | G8: =IF($C8="","",Calculadora!$C$15) | H8: =IF($C8="","",E8-F8-G8-D8) | I8: =IF($C8="","",IF(D8=0,0,(E8-F8-G8)/D8)) | J8: =IF($C8="","",IF(E8=0,0,H8/E8))
D9: =IF($C9="","",C9*(1+Calculadora!$C$12)) | E9: =IF($C9="","",D9*Calculadora!$C$13) | F9: =IF($C9="","",E9*Calculadora!$C$14) | G9: =IF($C9="","",Calculadora!$C$15) | H9: =IF($C9="","",E9-F9-G9-D9) | I9: =IF($C9="","",IF(D9=0,0,(E9-F9-G9)/D9)) | J9: =IF($C9="","",IF(E9=0,0,H9/E9))
D10: =IF($C10="","",C10*(1+Calculadora!$C$12)) | E10: =IF($C10="","",D10*Calculadora!$C$13) | F10: =IF($C10="","",E10*Calculadora!$C$14) | G10: =IF($C10="","",Calculadora!$C$15) | H10: =IF($C10="","",E10-F10-G10-D10) | I10: =IF($C10="","",IF(D10=0,0,(E10-F10-G10)/D10)) | J10: =IF($C10="","",IF(E10=0,0,H10/E10))
D11: =IF($C11="","",C11*(1+Calculadora!$C$12)) | E11: =IF($C11="","",D11*Calculadora!$C$13) | F11: =IF($C11="","",E11*Calculadora!$C$14) | G11: =IF($C11="","",Calculadora!$C$15) | H11: =IF($C11="","",E11-F11-G11-D11) | I11: =IF($C11="","",IF(D11=0,0,(E11-F11-G11)/D11)) | J11: =IF($C11="","",IF(E11=0,0,H11/E11))
D12: =IF($C12="","",C12*(1+Calculadora!$C$12)) | E12: =IF($C12="","",D12*Calculadora!$C$13) | F12: =IF($C12="","",E12*Calculadora!$C$14) | G12: =IF($C12="","",Calculadora!$C$15) | H12: =IF($C12="","",E12-F12-G12-D12) | I12: =IF($C12="","",IF(D12=0,0,(E12-F12-G12)/D12)) | J12: =IF($C12="","",IF(E12=0,0,H12/E12))
D13: =IF($C13="","",C13*(1+Calculadora!$C$12)) | E13: =IF($C13="","",D13*Calculadora!$C$13) | F13: =IF($C13="","",E13*Calculadora!$C$14) | G13: =IF($C13="","",Calculadora!$C$15) | H13: =IF($C13="","",E13-F13-G13-D13) | I13: =IF($C13="","",IF(D13=0,0,(E13-F13-G13)/D13)) | J13: =IF($C13="","",IF(E13=0,0,H13/E13))
D14: =IF($C14="","",C14*(1+Calculadora!$C$12)) | E14: =IF($C14="","",D14*Calculadora!$C$13) | F14: =IF($C14="","",E14*Calculadora!$C$14) | G14: =IF($C14="","",Calculadora!$C$15) | H14: =IF($C14="","",E14-F14-G14-D14) | I14: =IF($C14="","",IF(D14=0,0,(E14-F14-G14)/D14)) | J14: =IF($C14="","",IF(E14=0,0,H14/E14))
D15: =IF($C15="","",C15*(1+Calculadora!$C$12)) | E15: =IF($C15="","",D15*Calculadora!$C$13) | F15: =IF($C15="","",E15*Calculadora!$C$14) | G15: =IF($C15="","",Calculadora!$C$15) | H15: =IF($C15="","",E15-F15-G15-D15) | I15: =IF($C15="","",IF(D15=0,0,(E15-F15-G15)/D15)) | J15: =IF($C15="","",IF(E15=0,0,H15/E15))
D16: =IF($C16="","",C16*(1+Calculadora!$C$12)) | E16: =IF($C16="","",D16*Calculadora!$C$13) | F16: =IF($C16="","",E16*Calculadora!$C$14) | G16: =IF($C16="","",Calculadora!$C$15) | H16: =IF($C16="","",E16-F16-G16-D16) | I16: =IF($C16="","",IF(D16=0,0,(E16-F16-G16)/D16)) | J16: =IF($C16="","",IF(E16=0,0,H16/E16))
D17: =IF($C17="","",C17*(1+Calculadora!$C$12)) | E17: =IF($C17="","",D17*Calculadora!$C$13) | F17: =IF($C17="","",E17*Calculadora!$C$14) | G17: =IF($C17="","",Calculadora!$C$15) | H17: =IF($C17="","",E17-F17-G17-D17) | I17: =IF($C17="","",IF(D17=0,0,(E17-F17-G17)/D17)) | J17: =IF($C17="","",IF(E17=0,0,H17/E17))
D18: =IF($C18="","",C18*(1+Calculadora!$C$12)) | E18: =IF($C18="","",D18*Calculadora!$C$13) | F18: =IF($C18="","",E18*Calculadora!$C$14) | G18: =IF($C18="","",Calculadora!$C$15) | H18: =IF($C18="","",E18-F18-G18-D18) | I18: =IF($C18="","",IF(D18=0,0,(E18-F18-G18)/D18)) | J18: =IF($C18="","",IF(E18=0,0,H18/E18))
D19: =IF($C19="","",C19*(1+Calculadora!$C$12)) | E19: =IF($C19="","",D19*Calculadora!$C$13) | F19: =IF($C19="","",E19*Calculadora!$C$14) | G19: =IF($C19="","",Calculadora!$C$15) | H19: =IF($C19="","",E19-F19-G19-D19) | I19: =IF($C19="","",IF(D19=0,0,(E19-F19-G19)/D19)) | J19: =IF($C19="","",IF(E19=0,0,H19/E19))
D20: =IF($C20="","",C20*(1+Calculadora!$C$12)) | E20: =IF($C20="","",D20*Calculadora!$C$13) | F20: =IF($C20="","",E20*Calculadora!$C$14) | G20: =IF($C20="","",Calculadora!$C$15) | H20: =IF($C20="","",E20-F20-G20-D20) | I20: =IF($C20="","",IF(D20=0,0,(E20-F20-G20)/D20)) | J20: =IF($C20="","",IF(E20=0,0,H20/E20))
... D67: =IF($C67="","",C67*(1+Calculadora!$C$12)) | E67: =IF($C67="","",D67*Calculadora!$C$13) | F67: =IF($C67="","",E67*Calculadora!$C$14) | G67: =IF($C67="","",Calculadora!$C$15) | H67: =IF($C67="","",E67-F67-G67-D67) | I67: =IF($C67="","",IF(D67=0,0,(E67-F67-G67)/D67)) | J67: =IF($C67="","",IF(E67=0,0,H67/E67))
B69: Lucro = venda − Simples − frete − custo c/ DIFAL · Markup final = (venda − Simples − frete) ÷ custo c/ DIFAL
